django_usda_mongo-0.1.1.dist-info/DESCRIPTION.rst
django_usda_mongo-0.1.1.dist-info/METADATA
django_usda_mongo-0.1.1.dist-info/metadata.json
django_usda_mongo-0.1.1.dist-info/RECORD
django_usda_mongo-0.1.1.dist-info/top_level.txt
django_usda_mongo-0.1.1.dist-info/WHEEL
usda_mongo/__init__.py
usda_mongo/admin.py
usda_mongo/models.py
usda_mongo/mongoadmin.py
usda_mongo/urls.py
usda_mongo/views.py
usda_mongo/management/__init__.py
usda_mongo/management/commands/__init__.py
usda_mongo/management/commands/import_sr22.py
usda_mongo/management/commands/unicode_dict_reader.py
usda_mongo/migrations/__init__.py
