Metadata-Version: 2.0
Name: django-usda-mongo
Version: 0.1.1
Summary: Import and map the USDA National Nutrient Database for Standard Reference (SR22) to Django models using MongoDB with mongoengine
Home-page: https://github.com/javipalanca/django-usda-mongo
Author: Javi Palanca
Author-email: jpalanca@codemaniacs.com
License: BSD
Keywords: django-usda-mongo
Platform: UNKNOWN
Classifier: Development Status :: 2 - Pre-Alpha
Classifier: Framework :: Django
Classifier: Intended Audience :: Developers
Classifier: License :: OSI Approved :: BSD License
Classifier: Natural Language :: English
Classifier: Programming Language :: Python :: 2
Classifier: Programming Language :: Python :: 2.6
Classifier: Programming Language :: Python :: 2.7
Classifier: Programming Language :: Python :: 3
Classifier: Programming Language :: Python :: 3.3
